google_ssl/base.py
google_ssl/cli.py
google_ssl/common.py
google_ssl/deployer.py
google_ssl/rotator.py
google_ssl/service_account.py
google_ssl-0.1.0.dist-info/METADATA
google_ssl-0.1.0.dist-info/WHEEL
google_ssl-0.1.0.dist-info/entry_points.txt
google_ssl-0.1.0.dist-info/RECORD
