Metadata-Version: 2.1
Name: google-ssl
Version: 0.1.0
Summary: Google Cloud Function SSL Cert Rotator tool
Home-page: https://github.com/boltops-tools/google-ssl
License: Apache-2.0
Author: Tung Nguyen
Author-email: tongueroo@gmail.com
Requires-Python: >=3.11,<4.0
Classifier: License :: OSI Approved :: Apache Software License
Classifier: Programming Language :: Python :: 3
Classifier: Programming Language :: Python :: 3.11
Requires-Dist: click (>=8,<9)
Requires-Dist: functions-framework (>=3,<4)
Requires-Dist: google-api-python-client (>=2,<3)
Requires-Dist: google-cloud-compute (>=1,<2)
Requires-Dist: google-cloud-storage (>=2,<3)
